bergmann/__init__.py
bergmann/common/__init__.py
bergmann/common/exceptions.py
bergmann/common/logger.py
bergmann/common/ru_keys.py
bergmann/convention.py
bergmann/crypto/__init__.py
bergmann/crypto/kuzcypher.py
bergmann/di.py
bergmann/entities/__init__.py
bergmann/entities/header.py
bergmann/entities/item.py
bergmann/entities/load_items_result.py
bergmann/entities/store.py
bergmann/entities/store_meta.py
bergmann/failures_presenter.py
bergmann/files_helper.py
bergmann/interactor.py
bergmann/key.py
bergmann/main.py
bergmann/passwords_model.py
bergmann/ui/__init__.py
bergmann/ui/app.py
bergmann/ui/helpers.py
bergmann/ui/validators/__init__.py
bergmann/ui/validators/bmn_filename_validator.py
bergmann/ui/validators/file_already_exists_validator.py
bergmann/ui/widgets/__init__.py
bergmann/ui/widgets/passwords_modal/__init__.py
bergmann/ui/widgets/passwords_modal/initialize_new_db_modal.py
bergmann/ui/widgets/passwords_modal/item_fields_modal.py
bergmann/ui/widgets/passwords_modal/load_db_modal.py
bergmann/ui/widgets/passwords_modal/passwords_explorer.py
bergmann/ui/widgets/passwords_modal/passwords_table.py
bergmann/ui/widgets/select_file_modal/__init__.py
bergmann/ui/widgets/select_file_modal/bmn_filtered_directory_tree.py
bergmann/ui/widgets/select_file_modal/create_file_modal.py
bergmann/ui/widgets/select_file_modal/select_file_header.py
bergmann/ui/widgets/select_file_modal/select_file_modal.py
bergmann/ui/widgets/welcome.py
bergmann-1.0.1.dist-info/entry_points.txt
bergmann-1.0.1.dist-info/LICENSE
bergmann-1.0.1.dist-info/METADATA
bergmann-1.0.1.dist-info/WHEEL
bergmann-1.0.1.dist-info/RECORD
